cockatoo/__init__.py
cockatoo/cli.py
cockatoo/hclust.py
cockatoo/metric.py
cockatoo/screen.py
cockatoo/xtuition.py
cockatoo-0.6.2.dist-info/AUTHORS
cockatoo-0.6.2.dist-info/LICENSE
cockatoo-0.6.2.dist-info/METADATA
cockatoo-0.6.2.dist-info/WHEEL
cockatoo-0.6.2.dist-info/entry_points.txt
cockatoo-0.6.2.dist-info/top_level.txt
cockatoo-0.6.2.dist-info/RECORD
