Metadata-Version: 2.1
Name: cockatoo
Version: 0.6.2
Summary: cockatoo - A similarity metric for macromolecular crystallization conditions
Home-page: https://github.com/ubccr/cockatoo
Author: Andrew E. Bruno
Author-email: aebruno2@buffalo.edu
License: GNU General Public License v3 (GPLv3)
Platform: UNKNOWN
Classifier: Development Status :: 3 - Alpha
Classifier: Environment :: Console
Classifier: Intended Audience :: Developers
Classifier: Intended Audience :: Science/Research
Classifier: Programming Language :: Python
Classifier: License :: OSI Approved :: GNU General Public License v3 (GPLv3)
Classifier: Topic :: Scientific/Engineering :: Bio-Informatics
Requires-Dist: Click
Requires-Dist: e3fp
Requires-Dist: marshmallow (>=2.15.1)
Requires-Dist: numpy
Requires-Dist: scipy
Requires-Dist: matplotlib
Requires-Dist: requests
